<?xml version="1.0" encoding="UTF-8"?>
<!DOCTYPE mapper PUBLIC "-//mybatis.org//DTD Mapper 3.0//EN" "http://mybatis.org/dtd/mybatis-3-mapper.dtd">
<mapper namespace="com.ritoinfo.framework.evo.sp.sys.dao.FuncDao">

	<resultMap id="FuncResultMap" type="Func">
		<id column="id" property="id"/>
		<result column="micro_id" property="microId"/>
		<result column="name" property="name"/>
		<result column="code" property="code"/>
		<result column="uri" property="uri"/>
		<result column="method" property="method"/>
		<result column="create_by" property="createBy"/>
		<result column="create_time" property="createTime"/>
		<result column="update_by" property="updateBy"/>
		<result column="update_time" property="updateTime"/>
	</resultMap>

	<sql id="columns">
		t.id, t.micro_id, t.name, t.code, t.uri, t.method,
		t.create_by, t.create_time, t.update_by, t.update_time
	</sql>

	<sql id="condition">
		<where>
			<if test="id != null and id != ''">
				AND t.id = #{id}
			</if>
			<if test="microId != null and microId != ''">
				AND t.micro_id = #{microId}
			</if>
			<if test="name != null and name != ''">
				AND t.name = #{name}
			</if>
			<if test="code != null and code != ''">
				AND t.code = #{code}
			</if>
			<if test="uri != null and uri != ''">
				AND t.uri = #{uri}
			</if>
			<if test="method != null and method != ''">
				AND t.method = #{method}
			</if>
		</where>
	</sql>

	<sql id="conditionLike">
		<where>
			<if test="microId != null and microId != ''">
				AND t.micro_id = #{microId}
			</if>
			<if test="name != null and name != ''">
				AND t.name like '%${name}%'
			</if>
			<if test="code != null and code != ''">
				AND t.code like '%${code}%'
			</if>
			<if test="uri != null and uri != ''">
				AND t.uri like '%${uri}%'
			</if>
			<if test="method != null and method != ''">
				AND t.method = #{method}
			</if>
		</where>
	</sql>

	<sql id="select">
		SELECT <include refid="columns"/> FROM sys_func t
	</sql>

	<select id="get" resultMap="FuncResultMap">
		<include refid="select"/>
		WHERE t.id = #{value}
	</select>

	<select id="getWithMicro" resultType="map">
		SELECT
			t0.id, t0.micro_id, t0.name, t0.code, t0.uri, t0.method,
			t0.create_by, t0.create_time, t0.update_by, t0.update_time,
			t1.name micro_name
		  FROM sys_func t0
		  JOIN sys_micro t1 ON t0.micro_id = t1.id
		 WHERE t0.id = #{value}
	</select>

	<select id="find" resultMap="FuncResultMap">
		<include refid="select"/>
		<include refid="condition"/>
		<if test="pageSort != null">
			ORDER BY ${pageSort} <if test="pageOrder != null">${pageOrder}</if>
		</if>
	</select>

	<select id="findLike" resultMap="FuncResultMap">
		<include refid="select"/>
		<include refid="conditionLike"/>
		<if test="pageSort != null">
			ORDER BY ${pageSort} <if test="pageOrder != null">${pageOrder}</if>
		</if>
	</select>

	<select id="findPageWithMicro" resultType="map">
		SELECT
			t0.id, t0.micro_id, t0.name, t0.code, t0.uri, t0.method,
			t0.create_by, t0.create_time, t0.update_by, t0.update_time,
			t1.name micro_name
		  FROM sys_func t0
		  JOIN sys_micro t1 ON t0.micro_id = t1.id
		<where>
			<if test="microId != null and microId != ''">
				AND t0.micro_id = #{microId}
			</if>
			<if test="name != null and name != ''">
				AND t0.name like '%${name}%'
			</if>
			<if test="code != null and code != ''">
				AND t0.code like '%${code}%'
			</if>
			<if test="uri != null and uri != ''">
				AND t0.uri like '%${uri}%'
			</if>
			<if test="method != null and method != ''">
				AND t0.method = #{method}
			</if>
		</where>
	</select>

	<select id="findByRoleWithMicro" resultType="map">
		SELECT
			t0.id, t0.micro_id, t0.name, t0.code, t0.uri, t0.method,
			t0.create_by, t0.create_time, t0.update_by, t0.update_time,
			t2.name micro_name
		  FROM sys_func t0
		  JOIN sys_role_func t1 ON t0.id = t1.func_id
		  JOIN sys_micro t2 ON t0.micro_id = t2.id
		 WHERE t1.role_id = #{value}
	</select>

	<select id="findByPermission" resultType="map">
		SELECT
			t0.prefix,
			t1.uri,
			t1.method
		  FROM sys_micro t0
		  JOIN sys_func t1 ON t0.id = t1.micro_id
		  JOIN sys_role_func t2 ON t1.id = t2.func_id
		  JOIN sys_user_role t3 ON t2.role_id = t3.role_id
		 WHERE t3.user_id = #{userId}
		   AND t1.method = #{method}
	</select>

	<select id="findByUsername" resultType="map">
		SELECT
			t0.prefix,
			t1.uri,
			t1.method
		FROM sys_micro t0
		JOIN sys_func t1 ON t0.id = t1.micro_id
		JOIN sys_role_func t2 ON t1.id = t2.func_id
		JOIN sys_user_role t3 ON t2.role_id = t3.role_id
		JOIN sys_user t4 ON t3.user_id = t4.id
		WHERE t4.username = #{value}
	</select>

	<select id="count" resultType="int">
		SELECT count(1) count FROM sys_func t
		<include refid="condition"/>
	</select>

	<select id="countLike" resultType="int">
		SELECT count(1) count FROM sys_func t
		<include refid="conditionLike"/>
	</select>

	<select id="countWithMicro" resultType="int">
		SELECT
			count(1) count
		FROM sys_func t0
		JOIN sys_micro t1 ON t0.micro_id = t1.id
		<where>
			<if test="microId != null and microId != ''">
				AND t0.micro_id = #{microId}
			</if>
			<if test="name != null and name != ''">
				AND t0.name like '%${name}%'
			</if>
			<if test="code != null and code != ''">
				AND t0.code like '%${code}%'
			</if>
			<if test="uri != null and uri != ''">
				AND t0.uri like '%${uri}%'
			</if>
			<if test="method != null and method != ''">
				AND t0.method = #{method}
			</if>
		</where>
	</select>

	<insert id="insert" useGeneratedKeys="true" keyProperty="id">
		INSERT INTO sys_func (
			micro_id, name, code, uri, method, create_by, create_time, update_by, update_time
		) VALUES (
			#{microId}, #{name}, #{code}, #{uri}, #{method}, #{createBy}, #{createTime}, #{updateBy}, #{updateTime}
		)
	</insert>

	<update id="update">
		UPDATE sys_func SET
			micro_id = #{microId},
			name = #{name},
			code = #{code},
			uri = #{uri},
			method = #{method},
			update_by = #{updateBy},
			update_time = #{updateTime}
		WHERE
			id = #{id}
	</update>

	<delete id="delete">
		DELETE FROM sys_func WHERE id = #{value}
	</delete>

</mapper>
